Workbook

Sheet Dashboard
A1: StepEdge Offshore Call Centre – Dashboard
A2: All outputs are formulas driven by the Inputs sheet and the seat ramp on Monthly P&L.
A4: Metric | B4: Year 1 | C4: Year 2 | D4: Year 3 | E4: 36 months
A5: Revenue (R) | B5: =SUM('Monthly P&L'!B7:M7) | C5: =SUM('Monthly P&L'!N7:Y7) | D5: =SUM('Monthly P&L'!Z7:AK7) | E5: =SUM(B5:D5)
A6: Operating costs (R) | B6: =SUM('Monthly P&L'!B12:M12) | C6: =SUM('Monthly P&L'!N12:Y12) | D6: =SUM('Monthly P&L'!Z12:AK12) | E6: =SUM(B6:D6)
A7: GBS incentive (R) | B7: =SUM('Monthly P&L'!B14:M14) | C7: =SUM('Monthly P&L'!N14:Y14) | D7: =SUM('Monthly P&L'!Z14:AK14) | E7: =SUM(B7:D7)
A8: EBITDA pre-tax (R) | B8: =SUM('Monthly P&L'!B15:M15) | C8: =SUM('Monthly P&L'!N15:Y15) | D8: =SUM('Monthly P&L'!Z15:AK15) | E8: =SUM(B8:D8)
A9: Setup capex (R) | B9: =SUM('Monthly P&L'!B17:M17) | C9: =SUM('Monthly P&L'!N17:Y17) | D9: =SUM('Monthly P&L'!Z17:AK17) | E9: =SUM(B9:D9)
A10: Net cash flow (R) | B10: =SUM('Monthly P&L'!B18:M18) | C10: =SUM('Monthly P&L'!N18:Y18) | D10: =SUM('Monthly P&L'!Z18:AK18) | E10: =SUM(B10:D10)
A11: EBITDA margin | B11: =IFERROR(B8/B5,0) | C11: =IFERROR(C8/C5,0) | D11: =IFERROR(D8/D5,0) | E11: =IFERROR(E8/E5,0)
A12: Billed seats at year end | B12: ='Monthly P&L'!M4 | C12: ='Monthly P&L'!Y4 | D12: ='Monthly P&L'!AK4
A14: Key indicators
A15: Peak funding requirement (lowest cumulative cash, R) | B15: =MIN(0,MIN('Monthly P&L'!B19:AK19))
A16: Month of lowest cumulative cash | B16: =MATCH(MIN('Monthly P&L'!B19:AK19),'Monthly P&L'!B19:AK19,0)
A17: First month with positive EBITDA | B17: =IF(COUNT('Monthly P&L'!B20:AK20)=0,"Not within 36 months",MIN('Monthly P&L'!B20:AK20))
A18: Cash payback month (cumulative cash back above zero) | B18: =IF(COUNT('Monthly P&L'!B21:AK21)=0,"Not within 36 months",MIN('Monthly P&L'!B21:AK21))
A19: Margin per staffed seat incl. GBS (R / month) | B19: ='Seat Economics'!B15
A20: Margin % per seat (100% utilisation, excl. GBS) | B20: ='Seat Economics'!C12
A22: Illustrative model from public benchmarks (see research document). Not supplier quotes; excludes corporate tax, VAT and financing costs.

Sheet Inputs
A1: StepEdge Offshore Call Centre – Inputs
A2: Legend: blue text on yellow = input you can change · black = formula · green = link from another sheet. All rand figures are per month unless stated.
A4: Assumption | B4: Value | C4: Unit | D4: Source / note
A5: Pricing & FX
A6: Exchange rate | B6: 18 | C6: ZAR per US$ | D6: Assumption – update to current rate
A7: Price per dedicated seat | B7: 1600 | C7: US$ / seat / month | D7: Market range US$1,200–2,200 (CallForce, Afrishore, Callrica)
A8: Agent cost
A9: Agent basic salary | B9: 9000 | C9: R / month | D9: SA 2026: entry R6.5k–8.5k, experienced R8.5k–12k (ShiftMate)
A10: Loaded-cost multiplier | B10: 1.4 | C10: x basic | D10: UIF, SDL, leave, bonus, training. Industry 1.4–1.8x
A11: Supervision
A12: Team leader salary | B12: 25000 | C12: R / month | D12: Assumption
A13: Agents per team leader | B13: 15 | C13: agents | D13: Industry norm 12–15
A14: QA / workforce mgmt per seat | B14: 470 | C14: R / seat | D14: Assumption
A15: Seat running costs
A16: Office space per seat | B16: 1500 | C16: R / seat | D16: Serviced / shared office assumption
A17: Backup power & redundant connectivity per seat | B17: 1200 | C17: R / seat | D17: UPS/generator/solar + 2 lines
A18: Technology & telephony per seat | B18: 2000 | C18: R / seat | D18: CCaaS, CRM, international minutes, PC & headset amortised
A19: Fixed overheads
A20: Fixed overheads (management, UK/US sales, legal, admin) | B20: 75000 | C20: R / month | D20: Equals R1,500/seat at 50 seats
A21: Reference seat count for per-seat view | B21: 50 | C21: seats | D21: Used only on Seat Economics sheet
A22: Operations
A23: Seat utilisation (billed ÷ staffed) | B23: 0.9 | C23: % | D23: Target 80–90%
A24: Annual staff attrition | B24: 0.4 | C24: % / year | D24: SA call centres 30–50%
A25: Training cost per new hire | B25: 14500 | C25: R / hire | D25: ~5 weeks unbilled loaded wage
A26: Setup capex per new seat | B26: 18000 | C26: R / seat (once-off) | D26: PC, headset, furniture, licences setup
A27: GBS incentive
A28: Include GBS incentive? (1 = yes, 0 = no) | B28: 1 | C28: flag | D28: Requires 3-yr offshore contract, 50 jobs in 3 yrs, B-BBEE
A29: GBS grant per offshore job over 5 years | B29: 134000 | C29: R / job | D29: dtic: R134k (non-complex) to R280k (highly complex)
A30: First month incentive is received | B30: 19 | C30: month # | D30: Assumption: after first 3-yr contract approved

Sheet Seat Economics
A1: Unit economics of one billed seat (per month)
A3: Line | B3: R / month | C3: % of price
A4: Seat price (ZAR) | B4: =Inputs!$B$7*Inputs!$B$6 | C4: =IFERROR(B4/$B$4,0)
A5: Agent wage (loaded) | B5: =-Inputs!$B$9*Inputs!$B$10 | C5: =IFERROR(B5/$B$4,0)
A6: Team lead & QA | B6: =-(Inputs!$B$12*Inputs!$B$10/Inputs!$B$13+Inputs!$B$14) | C6: =IFERROR(B6/$B$4,0)
A7: Office space | B7: =-Inputs!$B$16 | C7: =IFERROR(B7/$B$4,0)
A8: Power & connectivity | B8: =-Inputs!$B$17 | C8: =IFERROR(B8/$B$4,0)
A9: Technology & telephony | B9: =-Inputs!$B$18 | C9: =IFERROR(B9/$B$4,0)
A10: Fixed overhead allocation | B10: =-Inputs!$B$20/Inputs!$B$21 | C10: =IFERROR(B10/$B$4,0)
A11: Total cost per seat | B11: =-SUM(B5:B10) | C11: =IFERROR(B11/$B$4,0)
A12: Margin per seat (100% utilisation) | B12: =B4-B11 | C12: =IFERROR(B12/$B$4,0)
A13: Margin per staffed seat at utilisation | B13: =B4*Inputs!$B$23-B11 | C13: =IFERROR(B13/$B$4,0)
A14: GBS incentive per job (5-yr average) | B14: =Inputs!$B$29/60*Inputs!$B$28 | C14: =IFERROR(B14/$B$4,0)
A15: Margin per staffed seat incl. GBS | B15: =B13+B14 | C15: =IFERROR(B15/$B$4,0)
A17: Note: GBS grant tapers over 5 years; a flat average is a simplification. Utilisation means part of staffed capacity is unbilled.
A19: Sensitivity: margin % per seat (100% utilisation, excl. GBS) – price vs exchange rate
A20: Price US$ ↓ / ZAR per US$ → | B20: 16 | C20: 17 | D20: 18 | E20: 19 | F20: 20
A21: 1200 | B21: =IFERROR(($A21*B$20-$B$11)/($A21*B$20),0) | C21: =IFERROR(($A21*C$20-$B$11)/($A21*C$20),0) | D21: =IFERROR(($A21*D$20-$B$11)/($A21*D$20),0) | E21: =IFERROR(($A21*E$20-$B$11)/($A21*E$20),0) | F21: =IFERROR(($A21*F$20-$B$11)/($A21*F$20),0)
A22: 1400 | B22: =IFERROR(($A22*B$20-$B$11)/($A22*B$20),0) | C22: =IFERROR(($A22*C$20-$B$11)/($A22*C$20),0) | D22: =IFERROR(($A22*D$20-$B$11)/($A22*D$20),0) | E22: =IFERROR(($A22*E$20-$B$11)/($A22*E$20),0) | F22: =IFERROR(($A22*F$20-$B$11)/($A22*F$20),0)
A23: 1600 | B23: =IFERROR(($A23*B$20-$B$11)/($A23*B$20),0) | C23: =IFERROR(($A23*C$20-$B$11)/($A23*C$20),0) | D23: =IFERROR(($A23*D$20-$B$11)/($A23*D$20),0) | E23: =IFERROR(($A23*E$20-$B$11)/($A23*E$20),0) | F23: =IFERROR(($A23*F$20-$B$11)/($A23*F$20),0)
A24: 1800 | B24: =IFERROR(($A24*B$20-$B$11)/($A24*B$20),0) | C24: =IFERROR(($A24*C$20-$B$11)/($A24*C$20),0) | D24: =IFERROR(($A24*D$20-$B$11)/($A24*D$20),0) | E24: =IFERROR(($A24*E$20-$B$11)/($A24*E$20),0) | F24: =IFERROR(($A24*F$20-$B$11)/($A24*F$20),0)
A25: 2000 | B25: =IFERROR(($A25*B$20-$B$11)/($A25*B$20),0) | C25: =IFERROR(($A25*C$20-$B$11)/($A25*C$20),0) | D25: =IFERROR(($A25*D$20-$B$11)/($A25*D$20),0) | E25: =IFERROR(($A25*E$20-$B$11)/($A25*E$20),0) | F25: =IFERROR(($A25*F$20-$B$11)/($A25*F$20),0)
A26: 2200 | B26: =IFERROR(($A26*B$20-$B$11)/($A26*B$20),0) | C26: =IFERROR(($A26*C$20-$B$11)/($A26*C$20),0) | D26: =IFERROR(($A26*D$20-$B$11)/($A26*D$20),0) | E26: =IFERROR(($A26*E$20-$B$11)/($A26*E$20),0) | F26: =IFERROR(($A26*F$20-$B$11)/($A26*F$20),0)

Sheet Monthly P&L
A1: 36-month P&L and cash (ZAR) – enter billed seat ramp in row 4
A3: Month | B3: 1 | C3: 2 | D3: 3 | E3: 4 | F3: 5 | G3: 6 | H3: 7 | I3: 8 | J3: 9 | K3: 10 | L3: 11 | M3: 12 | N3: 13 | O3: 14 | P3: 15 | Q3: 16 | R3: 17 | S3: 18 | T3: 19 | U3: 20 | V3: 21 | W3: 22 | X3: 23 | Y3: 24 | Z3: 25 | AA3: 26 | AB3: 27 | AC3: 28 | AD3: 29 | AE3: 30 | AF3: 31 | AG3: 32 | AH3: 33 | AI3: 34 | AJ3: 35 | AK3: 36
A4: Billed seats (input) | B4: 5 | C4: 5 | D4: 10 | E4: 10 | F4: 10 | G4: 15 | H4: 15 | I4: 15 | J4: 25 | K4: 25 | L4: 25 | M4: 30 | N4: 30 | O4: 30 | P4: 40 | Q4: 40 | R4: 40 | S4: 50 | T4: 50 | U4: 50 | V4: 50 | W4: 50 | X4: 50 | Y4: 60 | Z4: 60 | AA4: 60 | AB4: 60 | AC4: 60 | AD4: 60 | AE4: 70 | AF4: 70 | AG4: 70 | AH4: 70 | AI4: 70 | AJ4: 70 | AK4: 80
A5: Staffed seats | B5: =IFERROR(ROUNDUP(B4/Inputs!$B$23,0),0) | C5: =IFERROR(ROUNDUP(C4/Inputs!$B$23,0),0) | D5: =IFERROR(ROUNDUP(D4/Inputs!$B$23,0),0) | E5: =IFERROR(ROUNDUP(E4/Inputs!$B$23,0),0) | F5: =IFERROR(ROUNDUP(F4/Inputs!$B$23,0),0) | G5: =IFERROR(ROUNDUP(G4/Inputs!$B$23,0),0) | H5: =IFERROR(ROUNDUP(H4/Inputs!$B$23,0),0) | I5: =IFERROR(ROUNDUP(I4/Inputs!$B$23,0),0) | ... AK5: =IFERROR(ROUNDUP(AK4/Inputs!$B$23,0),0)
A6: New seats added | B6: =MAX(0,B5-0) | C6: =MAX(0,C5-B5) | D6: =MAX(0,D5-C5) | E6: =MAX(0,E5-D5) | F6: =MAX(0,F5-E5) | G6: =MAX(0,G5-F5) | H6: =MAX(0,H5-G5) | I6: =MAX(0,I5-H5) | J6: =MAX(0,J5-I5) | ... AK6: =MAX(0,AK5-AJ5)
A7: Revenue | B7: =B4*Inputs!$B$7*Inputs!$B$6 | C7: =C4*Inputs!$B$7*Inputs!$B$6 | D7: =D4*Inputs!$B$7*Inputs!$B$6 | E7: =E4*Inputs!$B$7*Inputs!$B$6 | F7: =F4*Inputs!$B$7*Inputs!$B$6 | G7: =G4*Inputs!$B$7*Inputs!$B$6 | H7: =H4*Inputs!$B$7*Inputs!$B$6 | I7: =I4*Inputs!$B$7*Inputs!$B$6 | ... AK7: =AK4*Inputs!$B$7*Inputs!$B$6
A8: Agent & supervision cost | B8: =-B5*(-'Seat Economics'!$B$5-'Seat Economics'!$B$6) | C8: =-C5*(-'Seat Economics'!$B$5-'Seat Economics'!$B$6) | D8: =-D5*(-'Seat Economics'!$B$5-'Seat Economics'!$B$6) | E8: =-E5*(-'Seat Economics'!$B$5-'Seat Economics'!$B$6) | F8: =-F5*(-'Seat Economics'!$B$5-'Seat Economics'!$B$6) | G8: =-G5*(-'Seat Economics'!$B$5-'Seat Economics'!$B$6) | H8: =-H5*(-'Seat Economics'!$B$5-'Seat Economics'!$B$6) | I8: =-I5*(-'Seat Economics'!$B$5-'Seat Economics'!$B$6) | ... AK8: =-AK5*(-'Seat Economics'!$B$5-'Seat Economics'!$B$6)
A9: Seat running costs | B9: =-B5*(Inputs!$B$16+Inputs!$B$17+Inputs!$B$18) | C9: =-C5*(Inputs!$B$16+Inputs!$B$17+Inputs!$B$18) | D9: =-D5*(Inputs!$B$16+Inputs!$B$17+Inputs!$B$18) | E9: =-E5*(Inputs!$B$16+Inputs!$B$17+Inputs!$B$18) | F9: =-F5*(Inputs!$B$16+Inputs!$B$17+Inputs!$B$18) | G9: =-G5*(Inputs!$B$16+Inputs!$B$17+Inputs!$B$18) | H9: =-H5*(Inputs!$B$16+Inputs!$B$17+Inputs!$B$18) | I9: =-I5*(Inputs!$B$16+Inputs!$B$17+Inputs!$B$18) | ... AK9: =-AK5*(Inputs!$B$16+Inputs!$B$17+Inputs!$B$18)
A10: Fixed overheads | B10: =-Inputs!$B$20 | C10: =-Inputs!$B$20 | D10: =-Inputs!$B$20 | E10: =-Inputs!$B$20 | F10: =-Inputs!$B$20 | G10: =-Inputs!$B$20 | H10: =-Inputs!$B$20 | I10: =-Inputs!$B$20 | ... AK10: =-Inputs!$B$20
A11: Attrition training cost | B11: =-(B5*Inputs!$B$24/12+B6)*Inputs!$B$25 | C11: =-(C5*Inputs!$B$24/12+C6)*Inputs!$B$25 | D11: =-(D5*Inputs!$B$24/12+D6)*Inputs!$B$25 | E11: =-(E5*Inputs!$B$24/12+E6)*Inputs!$B$25 | F11: =-(F5*Inputs!$B$24/12+F6)*Inputs!$B$25 | G11: =-(G5*Inputs!$B$24/12+G6)*Inputs!$B$25 | H11: =-(H5*Inputs!$B$24/12+H6)*Inputs!$B$25 | I11: =-(I5*Inputs!$B$24/12+I6)*Inputs!$B$25 | ... AK11: =-(AK5*Inputs!$B$24/12+AK6)*Inputs!$B$25
A12: Operating costs | B12: =SUM(B8:B11) | C12: =SUM(C8:C11) | D12: =SUM(D8:D11) | E12: =SUM(E8:E11) | F12: =SUM(F8:F11) | G12: =SUM(G8:G11) | H12: =SUM(H8:H11) | I12: =SUM(I8:I11) | ... AK12: =SUM(AK8:AK11)
A13: Gross operating profit (pre-incentive) | B13: =B7+B12 | C13: =C7+C12 | D13: =D7+D12 | E13: =E7+E12 | F13: =F7+F12 | G13: =G7+G12 | H13: =H7+H12 | I13: =I7+I12 | ... AK13: =AK7+AK12
A14: GBS incentive | B14: =IF(B$3>=Inputs!$B$30,B5*Inputs!$B$29/60*Inputs!$B$28,0) | C14: =IF(C$3>=Inputs!$B$30,C5*Inputs!$B$29/60*Inputs!$B$28,0) | D14: =IF(D$3>=Inputs!$B$30,D5*Inputs!$B$29/60*Inputs!$B$28,0) | E14: =IF(E$3>=Inputs!$B$30,E5*Inputs!$B$29/60*Inputs!$B$28,0) | F14: =IF(F$3>=Inputs!$B$30,F5*Inputs!$B$29/60*Inputs!$B$28,0) | G14: =IF(G$3>=Inputs!$B$30,G5*Inputs!$B$29/60*Inputs!$B$28,0) | H14: =IF(H$3>=Inputs!$B$30,H5*Inputs!$B$29/60*Inputs!$B$28,0) | I14: =IF(I$3>=Inputs!$B$30,I5*Inputs!$B$29/60*Inputs!$B$28,0) | ... AK14: =IF(AK$3>=Inputs!$B$30,AK5*Inputs!$B$29/60*Inputs!$B$28,0)
A15: EBITDA (pre-tax) | B15: =B13+B14 | C15: =C13+C14 | D15: =D13+D14 | E15: =E13+E14 | F15: =F13+F14 | G15: =G13+G14 | H15: =H13+H14 | I15: =I13+I14 | ... AK15: =AK13+AK14
A16: EBITDA margin | B16: =IFERROR(B15/B7,0) | C16: =IFERROR(C15/C7,0) | D16: =IFERROR(D15/D7,0) | E16: =IFERROR(E15/E7,0) | F16: =IFERROR(F15/F7,0) | G16: =IFERROR(G15/G7,0) | H16: =IFERROR(H15/H7,0) | I16: =IFERROR(I15/I7,0) | ... AK16: =IFERROR(AK15/AK7,0)
A17: Setup capex | B17: =-B6*Inputs!$B$26 | C17: =-C6*Inputs!$B$26 | D17: =-D6*Inputs!$B$26 | E17: =-E6*Inputs!$B$26 | F17: =-F6*Inputs!$B$26 | G17: =-G6*Inputs!$B$26 | H17: =-H6*Inputs!$B$26 | I17: =-I6*Inputs!$B$26 | ... AK17: =-AK6*Inputs!$B$26
A18: Net cash flow | B18: =B15+B17 | C18: =C15+C17 | D18: =D15+D17 | E18: =E15+E17 | F18: =F15+F17 | G18: =G15+G17 | H18: =H15+H17 | I18: =I15+I17 | ... AK18: =AK15+AK17
A19: Cumulative cash | B19: =B18 | C19: =C18+B19 | D19: =D18+C19 | E19: =E18+D19 | F19: =F18+E19 | G19: =G18+F19 | H19: =H18+G19 | I19: =I18+H19 | J19: =J18+I19 | ... AK19: =AK18+AJ19
A20: Helper: month if EBITDA > 0 | B20: =IF(B15>0,B$3,"") | C20: =IF(C15>0,C$3,"") | D20: =IF(D15>0,D$3,"") | E20: =IF(E15>0,E$3,"") | F20: =IF(F15>0,F$3,"") | G20: =IF(G15>0,G$3,"") | H20: =IF(H15>0,H$3,"") | I20: =IF(I15>0,I$3,"") | ... AK20: =IF(AK15>0,AK$3,"")
A21: Attrition training = monthly leavers (staffed × attrition ÷ 12) plus new seats, × training cost. Note: the billed-seat ramp in row 4 is an example – replace with your pipeline. | B21: =IF(AND(B19>=0,B$3>Dashboard!$B$16),B$3,"") | C21: =IF(AND(C19>=0,C$3>Dashboard!$B$16),C$3,"") | D21: =IF(AND(D19>=0,D$3>Dashboard!$B$16),D$3,"") | E21: =IF(AND(E19>=0,E$3>Dashboard!$B$16),E$3,"") | F21: =IF(AND(F19>=0,F$3>Dashboard!$B$16),F$3,"") | G21: =IF(AND(G19>=0,G$3>Dashboard!$B$16),G$3,"") | H21: =IF(AND(H19>=0,H$3>Dashboard!$B$16),H$3,"") | I21: =IF(AND(I19>=0,I$3>Dashboard!$B$16),I$3,"") | ... AK21: =IF(AND(AK19>=0,AK$3>Dashboard!$B$16),AK$3,"")
